ii/Notepad++.zip
ii/ProcessMonitor.zip
ii/__init__.py
ii/adb-tools.zip
ii/main.py
ii/nasm-2.14.02-win32.zip
ii/nasm-2.14.02-win64.zip
ii/ollydbg.zip
ii/procexp32.zip
ii/procexp64.zip
ii/tcc-0.9.27-win32-bin.zip
ii/tcc-0.9.27-win64-bin.zip
ii/upx-3.95-32.zip
ii/upx-3.95-64.zip
ii/winapi-full-for-0.9.27.zip
ii-0.1.2.dist-info/LICENSE
ii-0.1.2.dist-info/METADATA
ii-0.1.2.dist-info/WHEEL
ii-0.1.2.dist-info/entry_points.txt
ii-0.1.2.dist-info/top_level.txt
ii-0.1.2.dist-info/RECORD
