Metadata-Version: 2.1
Name: ii
Version: 0.1.2
Summary: my tools
Home-page: UNKNOWN
Author: cilame
Author-email: opaquisrm@hotmail.com
License: MIT
Keywords: ii
Platform: UNKNOWN
Classifier: License :: OSI Approved :: MIT License
Classifier: Programming Language :: Python
Classifier: Intended Audience :: Developers
Requires-Python: >=3.5
